tickthon/__init__.py
tickthon/_task_utils.py
tickthon/_ticktick_api.py
tickthon/py.typed
tickthon/task_model.py
tickthon/ticktick_client.py
tickthon/data/__init__.py
tickthon/data/ticktick_ids.py
tickthon/data/ticktick_list_parameters.py
tickthon/data/ticktick_payloads.py
tickthon/data/ticktick_task_parameters.py
tickthon-0.3.5.dist-info/licenses/LICENSE
tickthon-0.3.5.dist-info/METADATA
tickthon-0.3.5.dist-info/WHEEL
tickthon-0.3.5.dist-info/top_level.txt
tickthon-0.3.5.dist-info/RECORD
