Metadata-Version: 2.4
Name: tickthon
Version: 0.3.5
Summary: Yet another unofficial Ticktick API client, it is based on ticktick-py
Author-email: anggelomos <anggelomos@outlook.com>
Project-URL: repository, https://github.com/anggelomos/tickthon
Classifier: Programming Language :: Python :: 3.10
Requires-Python: >=3.10
License-File: LICENSE
Requires-Dist: requests
Requires-Dist: attrs
Requires-Dist: python-dateutil
Dynamic: license-file
